giftless_client/__init__.py
giftless_client/client.py
giftless_client/exc.py
giftless_client/main.py
giftless_client/transfer.py
giftless_client/types.py
giftless_client-0.1.1.dist-info/LICENSE
giftless_client-0.1.1.dist-info/METADATA
giftless_client-0.1.1.dist-info/WHEEL
giftless_client-0.1.1.dist-info/entry_points.txt
giftless_client-0.1.1.dist-info/top_level.txt
giftless_client-0.1.1.dist-info/RECORD
