Metadata-Version: 2.1
Name: giftless-client
Version: 0.1.1
Summary: A Git LFS client implementation in Python
Home-page: https://github.com/datopian/giftless-client
Author: Shahar Evron
Author-email: shahar.evron@datopian.com
License: UNKNOWN
Platform: UNKNOWN
Requires-Dist: click
Requires-Dist: requests
Requires-Dist: python-dateutil
Requires-Dist: typing-extensions
